kpler/sdk/__init__.py
kpler/sdk/client.py
kpler/sdk/configuration.py
kpler/sdk/enums.py
kpler/sdk/exceptions.py
kpler/sdk/helpers.py
kpler/sdk/resources/__init__.py
kpler/sdk/resources/ballast_capacity_port_calls.py
kpler/sdk/resources/ballast_capacity_series.py
kpler/sdk/resources/congestion_series.py
kpler/sdk/resources/congestion_vessels.py
kpler/sdk/resources/contract.py
kpler/sdk/resources/contracts.py
kpler/sdk/resources/fleet_development_series.py
kpler/sdk/resources/fleet_development_vessels.py
kpler/sdk/resources/fleet_metric.py
kpler/sdk/resources/fleet_metric_vessels.py
kpler/sdk/resources/fleet_metrics.py
kpler/sdk/resources/fleet_metrics_vessels.py
kpler/sdk/resources/fleet_utilization_series.py
kpler/sdk/resources/fleet_utilization_vessels.py
kpler/sdk/resources/flow.py
kpler/sdk/resources/flows.py
kpler/sdk/resources/freight_metric_series.py
kpler/sdk/resources/freight_metrics_series.py
kpler/sdk/resources/installation.py
kpler/sdk/resources/installations.py
kpler/sdk/resources/inventories.py
kpler/sdk/resources/inventories_tank_levels.py
kpler/sdk/resources/outage.py
kpler/sdk/resources/outages.py
kpler/sdk/resources/player.py
kpler/sdk/resources/players.py
kpler/sdk/resources/port_call.py
kpler/sdk/resources/port_calls.py
kpler/sdk/resources/price.py
kpler/sdk/resources/prices.py
kpler/sdk/resources/product.py
kpler/sdk/resources/products.py
kpler/sdk/resources/ship_to_ship.py
kpler/sdk/resources/ship_to_ships.py
kpler/sdk/resources/trade.py
kpler/sdk/resources/trades.py
kpler/sdk/resources/vessel.py
kpler/sdk/resources/vessels.py
kpler/sdk/resources/zone.py
kpler/sdk/resources/zones.py
kpler.sdk-1.0.3.dist-info/METADATA
kpler.sdk-1.0.3.dist-info/WHEEL
kpler.sdk-1.0.3.dist-info/top_level.txt
kpler.sdk-1.0.3.dist-info/RECORD
