Metadata-Version: 2.1
Name: kpler.sdk
Version: 1.0.3
Summary: A Python wrapper around the Kpler client API
Home-page: http://github.com/kpler/python-sdk
Author: Kpler
Author-email: engineering@kpler.com
License: MIT
Platform: UNKNOWN
Classifier: Programming Language :: Python :: 3
Classifier: Programming Language :: Python :: 3.7
Classifier: Programming Language :: Python :: 3.8
Classifier: Programming Language :: Python :: 3.9
Classifier: License :: OSI Approved :: MIT License
Classifier: Operating System :: OS Independent
Requires-Dist: pandas (>=1.1.4)
Requires-Dist: numpy (>=1.19.0)
Requires-Dist: requests (>=2.24.0)
Provides-Extra: doc
Requires-Dist: Sphinx (==3.2.1) ; extra == 'doc'
Requires-Dist: sphinx-rtd-theme (==0.5.0) ; extra == 'doc'
Requires-Dist: sphinx-autodoc-typehints (==1.6.0) ; extra == 'doc'
Provides-Extra: test
Requires-Dist: black (==18.9b0) ; extra == 'test'
Requires-Dist: mypy-extensions (==0.4.3) ; extra == 'test'
Requires-Dist: mypy (==0.782) ; extra == 'test'
Requires-Dist: pre-commit (==2.6.0) ; extra == 'test'
Requires-Dist: pytest (==4.0.0) ; extra == 'test'
